LICENSE
MANIFEST.in
README.rst
pasteraw.py
setup.py
pasteraw.egg-info/PKG-INFO
pasteraw.egg-info/SOURCES.txt
pasteraw.egg-info/dependency_links.txt
pasteraw.egg-info/entry_points.txt
pasteraw.egg-info/pbr.json
pasteraw.egg-info/requires.txt
pasteraw.egg-info/top_level.txt