Metadata-Version: 1.1
Name: pasteraw
Version: 1.1.0
Summary: Pipe stdin to a raw pastebin
Home-page: http://github.com/dolph/pasteraw-client
Author: Dolph Mathews
Author-email: dolph.mathews@gmail.com
License: UNKNOWN
Platform: UNKNOWN
Classifier: Development Status :: 5 - Production/Stable
Classifier: Environment :: Console
Classifier: Intended Audience :: Developers
Classifier: Topic :: Utilities
